crystpqdb/__init__.py
crystpqdb/_version.py
crystpqdb/db.py
crystpqdb/download.py
crystpqdb/loaders/README.md
crystpqdb/loaders/__init__.py
crystpqdb/loaders/alexandria.py
crystpqdb/loaders/base.py
crystpqdb/loaders/factory.py
crystpqdb/loaders/jarvis.py
crystpqdb/loaders/mc3d.py
crystpqdb/loaders/mp.py
crystpqdb/utils/__init__.py
crystpqdb/utils/log.py
crystpqdb/utils/pyarrow_utils.py
crystpqdb-0.0.1.dev31.dist-info/licenses/LICENSE
crystpqdb-0.0.1.dev31.dist-info/METADATA
crystpqdb-0.0.1.dev31.dist-info/WHEEL
crystpqdb-0.0.1.dev31.dist-info/entry_points.txt
crystpqdb-0.0.1.dev31.dist-info/top_level.txt
crystpqdb-0.0.1.dev31.dist-info/RECORD
