Metadata-Version: 2.4
Name: crystpqdb
Version: 0.0.1.dev31
Summary: A Python library for Crystal Parquet Database.
Author-email: Logan Lang <lllang@mix.wvu.edu>
License-Expression: MIT
Project-URL: homepage, https://github.com/llangWV/Crystal-Parquet-Database
Project-URL: documentation, https://llangWV.github.io/Crystal-Parquet-Database/
Project-URL: Issues, https://github.com/llangWV/Crystal-Parquet-Database/issues
Project-URL: Changelog, https://github.com/llangWV/Crystal-Parquet-Database/CHANGELOG.md
Classifier: Programming Language :: Python :: 3
Requires-Python: >=3.8
License-File: LICENSE
Dynamic: license-file
